xlambda_helper/__init__.py
xlambda_helper/constants.py
xlambda_helper/main.py
xlambda_helper-0.0.3.dist-info/LICENSE
xlambda_helper-0.0.3.dist-info/METADATA
xlambda_helper-0.0.3.dist-info/WHEEL
xlambda_helper-0.0.3.dist-info/top_level.txt
xlambda_helper-0.0.3.dist-info/RECORD
