Metadata-Version: 2.1
Name: xlambda-helper
Version: 0.0.3
Summary: Helper library to handle warming requests from X-Lambda (more: https://bit.ly/xlambda).
Home-page: https://github.com/dashbird/xlambda-helper-python/archive/0.0.3.tar.gz
Author: Dashbird.io (Renato Byrro)
Author-email: renato@dashbird.io
License: MIT
Keywords: x-lambda,xlambda,aws,aws lambda,cold start,warm,serverless,containers
Platform: UNKNOWN
Classifier: License :: OSI Approved :: MIT License
Classifier: Programming Language :: Python :: 3
Classifier: Programming Language :: Python :: 3.7
Classifier: Development Status :: 3 - Alpha
Classifier: Intended Audience :: Developers
Requires-Dist: boto3
